GitlabPyRunner/__init__.py
GitlabPyRunner/__main__.py
GitlabPyRunner/common.py
GitlabPyRunner/consts.py
GitlabPyRunner/executor.py
GitlabPyRunner/gitlab-runner-init.sh
GitlabPyRunner/httpclient.py
GitlabPyRunner/runner.py
GitlabPyRunner/service.py
GitlabPyRunner/tool.py
GitlabPyRunner/trace.py
gitlab_python_runner-14.3.20.data/scripts/gitlab-runner.py
gitlab_python_runner-14.3.20.dist-info/LICENSE
gitlab_python_runner-14.3.20.dist-info/METADATA
gitlab_python_runner-14.3.20.dist-info/WHEEL
gitlab_python_runner-14.3.20.dist-info/top_level.txt
gitlab_python_runner-14.3.20.dist-info/RECORD
