Metadata-Version: 2.1
Name: gitlab-python-runner
Version: 14.3.20
Summary: Pure python gitlab-runner
Home-page: https://gitlab.com/cunity/gitlab-python-runner
Author: Ian Norton
Author-email: inorton@gmail.com
License: License :: OSI Approved :: MIT License
Platform: any
License-File: LICENSE
Requires-Dist: pyyaml (>=5.1)
Requires-Dist: gitlab-emulator (>=0.11.1)
Requires-Dist: unidecode (>=1.1.1)
